sdnoise.cp38-win_amd64.pyd
sdnoise-1.0.0.dist-info/LICENSE.md
sdnoise-1.0.0.dist-info/METADATA
sdnoise-1.0.0.dist-info/WHEEL
sdnoise-1.0.0.dist-info/top_level.txt
sdnoise-1.0.0.dist-info/RECORD
