Metadata-Version: 2.1
Name: sdnoise
Version: 1.0.0
Summary: A Python wrapper for simplex noise functions with analytical derivatives.
Author-email: Oliver John Hitchcock <ojhitchcock@gmail.com>
License: 
Keywords: simplex,noise,procedural
Platform: any
License-File: LICENSE.md
